regex_patterns.py
regex_patterns-1.0.0.dist-info/METADATA
regex_patterns-1.0.0.dist-info/WHEEL
regex_patterns-1.0.0.dist-info/LICENSE
regex_patterns-1.0.0.dist-info/RECORD
